consumet_mc/__init__.py
consumet_mc/extractors/__init__.py
consumet_mc/extractors/asianload.py
consumet_mc/extractors/builtin.py
consumet_mc/extractors/engifuosi.py
consumet_mc/extractors/filemoon.py
consumet_mc/extractors/kk.py
consumet_mc/extractors/kwik.py
consumet_mc/extractors/mp4upload.py
consumet_mc/extractors/rabbitstream.py
consumet_mc/extractors/streamwish.py
consumet_mc/extractors/tukipasti.py
consumet_mc/extractors/upcloud.py
consumet_mc/extractors/vidcloud.py
consumet_mc/extractors/video_extractor.py
consumet_mc/extractors/vidmoly.py
consumet_mc/extractors/vidzcloud.py
consumet_mc/extractors/voe.py
consumet_mc/extractors/megacloud/megacloud.py
consumet_mc/extractors/megacloud/megacloud_decodedpng.py
consumet_mc/extractors/megacloud/megacloud_getsrcs.py
consumet_mc/models/__init__.py
consumet_mc/models/episode.py
consumet_mc/models/paged_result.py
consumet_mc/models/season.py
consumet_mc/models/source.py
consumet_mc/models/subtitle.py
consumet_mc/models/video.py
consumet_mc/models/video_server.py
consumet_mc/providers/__init__.py
consumet_mc/providers/allanime.py
consumet_mc/providers/animepahe.py
consumet_mc/providers/aniworld.py
consumet_mc/providers/dramacool.py
consumet_mc/providers/flixhq.py
consumet_mc/providers/hianime.py
consumet_mc/providers/himovies.py
consumet_mc/providers/kisskh.py
consumet_mc/providers/provider.py
consumet_mc/providers/sflix.py
consumet_mc/providers/turkish.py
consumet_mc/providers/viewasian.py
consumet_mc/utils/crypto.py
consumet_mc/utils/packer.py
consumet_mc/utils/utils.py
consumet_mc-1.1.1.dist-info/licenses/LICENSE
consumet_mc-1.1.1.dist-info/METADATA
consumet_mc-1.1.1.dist-info/WHEEL
consumet_mc-1.1.1.dist-info/top_level.txt
consumet_mc-1.1.1.dist-info/RECORD
