Metadata-Version: 2.4
Name: consumet-mc
Version: 1.1.1
Summary: A mov-cli plugin for watching Movies, Shows and Anime based off consumet.ts
License: MIT License
Project-URL: GitHub, https://github.com/yur3iDev/consumet-mc
Project-URL: BugTracker, https://github.com/yur3iDev/consumet-mc/issues
Keywords: mov-cli plugin,consumet
Classifier: Operating System :: Microsoft :: Windows :: Windows 11
Classifier: Operating System :: Microsoft :: Windows :: Windows 10
Classifier: Operating System :: POSIX :: Linux
Classifier: License :: OSI Approved :: MIT License
Classifier: Programming Language :: Python :: 3.8
Classifier: Programming Language :: Python :: 3.9
Classifier: Programming Language :: Python :: 3.10
Classifier: Programming Language :: Python :: 3.11
Classifier: Programming Language :: Python :: 3.12
Requires-Python: >=3.8
License-File: LICENSE
Requires-Dist: pycryptodome
Requires-Dist: importlib-metadata; python_version < "3.8"
Requires-Dist: mov-cli>=4.0.3
Provides-Extra: dev
Requires-Dist: ruff; extra == "dev"
Requires-Dist: build; extra == "dev"
Dynamic: license-file
